diraccfg/__init__.py
diraccfg/__main__.py
diraccfg/cfg.py
diraccfg/py.typed
diraccfg/versions.py
diraccfg-1.0.1.dist-info/LICENSE
diraccfg-1.0.1.dist-info/METADATA
diraccfg-1.0.1.dist-info/WHEEL
diraccfg-1.0.1.dist-info/entry_points.txt
diraccfg-1.0.1.dist-info/top_level.txt
diraccfg-1.0.1.dist-info/RECORD
