Metadata-Version: 2.1
Name: diraccfg
Version: 1.0.1
Summary: DIRAC cfg files reader
Home-page: https://github.com/DIRACGrid/cfg
Author: Federico Stagni
License: GPL-3.0-only
Classifier: Programming Language :: Python :: 3.9
Classifier: Programming Language :: Python :: 3.10
Classifier: Programming Language :: Python :: 3.11
Classifier: License :: OSI Approved :: GNU General Public License v3 (GPLv3)
Classifier: Operating System :: OS Independent
Requires-Python: >=3.9
License-File: LICENSE
Provides-Extra: testing
Requires-Dist: pytest >=4.6 ; extra == 'testing'
Requires-Dist: pytest-cov ; extra == 'testing'
Requires-Dist: pylint >=1.6.5 ; extra == 'testing'
